bin/AddGlobalInstallLogEntry.py
bin/BST.py
bin/BootstrapSIT.py
bin/CreateProxyDir.py
bin/ExecInAllProjects.py
bin/FindProxyInstallations.py
bin/ListDependencies.py
bin/MSVC-Setup.py
bin/ToolBOS-Config.py
bin/ToolBOS-Setup.py
bin/UpdateProxyDir.py
bin/Wine-Setup.py
bin/runKlocwork.py
bin/runSonarQube.py
bin/sitorphan.py
doc/BuildSystemTools/BuildSystemTools-Timeline.png
doc/BuildSystemTools/CMakeFromSIT.png
doc/BuildSystemTools/CMakeListOfGeneratorsOnWindows.png
doc/BuildSystemTools/CallingCMakeHelpPage.png
doc/BuildSystemTools/InTreeBuild.png
doc/BuildSystemTools/MapNetworkDrive-Win7.png
doc/BuildSystemTools/MapNetworkDrive-WinXP.png
doc/BuildSystemTools/OutOfTreeBuild1.png
doc/BuildSystemTools/OutOfTreeBuild2.png
doc/BuildSystemTools/RunCMakeOnWindows.png
doc/BuildSystemTools/RunWindowsBuildScript-SetupOnly.png
doc/BuildSystemTools/RunWindowsBuildScript-Win7.png
doc/BuildSystemTools/RunWindowsBuildScript-WinXP.png
doc/BuildSystemTools/TopLevelDirectory-Win7.png
doc/BuildSystemTools/TopLevelDirectory-WinXP.png
doc/BuildSystemTools/VisualStudio2010-WinXP.png
doc/BuildSystemTools/VisualStudio2012-Win7.png
doc/BuildSystemTools/VisualStudioBuild.png
doc/BuildSystemTools/VisualStudioOpenDialog.png
doc/BuildSystemTools/VisualStudioRunButton.png
doc/BuildSystemTools/VisualStudioSolutionFile.png
doc/BuildSystemTools/VisualStudioSwitchToRelease.png
doc/BuildSystemTools/WindowsBST.png
doc/BuildSystemTools/WindowsBuildDir.png
doc/BuildSystemTools/WindowsSetEnv.png
doc/BuildSystemTools/WindowsUnittest.png
doc/BuildSystemTools/ZenBuildMode-800x487.png
doc/BuildSystemTools/ZenBuildMode-SQCheck1-small.png
doc/BuildSystemTools/ZenBuildMode-SQCheck2-small.png
doc/Concepts/BuildSystem.png
doc/Concepts/PackageStructure.png
doc/Concepts/ProxyDirectory-DirListing.png
doc/Concepts/ProxyDirectory-DirListingGlobal.png
doc/Concepts/ProxyDirectory-DirListingProxy.png
doc/Concepts/ProxyDirectory-afterProxyInstall.png
doc/Concepts/ProxyDirectory.png
doc/Concepts/SIT-Structure.png
toolboscore-0.4.0.dist-info/LICENSE
toolboscore-0.4.0.dist-info/METADATA
toolboscore-0.4.0.dist-info/WHEEL
toolboscore-0.4.0.dist-info/top_level.txt
toolboscore-0.4.0.dist-info/RECORD
