Metadata-Version: 2.1
Name: toolboscore
Version: 0.4.0
Summary: Quality checks and routine
Author-email: HRI <monicadasi18@gmail.com>
Project-URL: Homepage, https://github.com/HRI-EU/ToolBOSCore
Classifier: Programming Language :: Python :: 3
Classifier: License :: OSI Approved :: BSD License
Classifier: Operating System :: OS Independent
Requires-Python: >=3.6
License-File: LICENSE
